opentelemetry/instrumentation/asyncpg/__init__.py
opentelemetry/instrumentation/asyncpg/package.py
opentelemetry/instrumentation/asyncpg/version.py
opentelemetry_instrumentation_asyncpg-0.60b0.dist-info/METADATA
opentelemetry_instrumentation_asyncpg-0.60b0.dist-info/WHEEL
opentelemetry_instrumentation_asyncpg-0.60b0.dist-info/entry_points.txt
opentelemetry_instrumentation_asyncpg-0.60b0.dist-info/licenses/LICENSE
opentelemetry_instrumentation_asyncpg-0.60b0.dist-info/RECORD
